CHANGES.rst
MANIFEST.in
README.rst
setup.py
wrap2/__init__.py
wrap2/core.py
wrap2/facebook.py
wrap2/twitter.py
wrap2.egg-info/PKG-INFO
wrap2.egg-info/SOURCES.txt
wrap2.egg-info/dependency_links.txt
wrap2.egg-info/requires.txt
wrap2.egg-info/top_level.txt