Metadata-Version: 1.0
Name: wrap2
Version: 0.9
Summary: Wrapper for social network wrappers
Home-page: UNKNOWN
Author: Paylogic International
Author-email: developers@paylogic.com
License: MIT
Platform: UNKNOWN
